fabianMontecarlo/__init__.py
fabianMontecarlo/modulo.py
fbMonteCarlo-0.2.0.dist-info/METADATA
fbMonteCarlo-0.2.0.dist-info/WHEEL
fbMonteCarlo-0.2.0.dist-info/top_level.txt
fbMonteCarlo-0.2.0.dist-info/RECORD
