Metadata-Version: 2.1
Name: fbMonteCarlo
Version: 0.2.0
Summary: libreria-integral-montecarlo
Home-page: UNKNOWN
Author: Fabian
Author-email: fyamith.tovar@udea.edu.co
License: MIT
Platform: UNKNOWN
Requires-Python: >=3.10.12
Requires-Dist: matplotlib (==3.8.1)
Requires-Dist: numpy (==1.26.1)
Requires-Dist: scipy (==1.11.3)
